Metadata-Version: 2.4
Name: mroudai-django-services
Version: 0.1.0
Summary: Reusable Django app for modelling bookable services, categories, and add-ons.
Author-email: Kevin Oudai <kevin@mroudai.com>
License: MIT License
Project-URL: Homepage, https://mroudai.com
Project-URL: Source, https://mroudai.com/projects/django-services
Project-URL: Issues, https://mroudai.com/contact
Classifier: Development Status :: 3 - Alpha
Classifier: Framework :: Django
Classifier: Framework :: Django :: 4.2
Classifier: Framework :: Django :: 5.0
Classifier: Framework :: Django :: 5.1
Classifier: License :: OSI Approved :: MIT License
Classifier: Operating System :: OS Independent
Classifier: Programming Language :: Python
Classifier: Programming Language :: Python :: 3
Classifier: Programming Language :: Python :: 3.10
Classifier: Programming Language :: Python :: 3.11
Classifier: Programming Language :: Python :: 3.12
Classifier: Programming Language :: Python :: 3.13
Classifier: Intended Audience :: Developers
Classifier: Topic :: Software Development :: Libraries :: Application Frameworks
Requires-Python: >=3.10
License-File: LICENSE
Requires-Dist: django>=4.2
Dynamic: license-file
